JustATest0/__init__.py
JustATest0/hello.py
hellopkgabcdefghijklmnop1-0.0.1.dist-info/METADATA
hellopkgabcdefghijklmnop1-0.0.1.dist-info/WHEEL
hellopkgabcdefghijklmnop1-0.0.1.dist-info/top_level.txt
hellopkgabcdefghijklmnop1-0.0.1.dist-info/RECORD
